nesco/__init__.py
nesco/main.py
nesco/nesco.py
nesco-1.4.0.dist-info/METADATA
nesco-1.4.0.dist-info/WHEEL
nesco-1.4.0.dist-info/entry_points.txt
nesco-1.4.0.dist-info/top_level.txt
nesco-1.4.0.dist-info/RECORD
