Metadata-Version: 2.4
Name: nesco
Version: 1.4.0
Summary: A Python module for Northern Electric Supply Company Limited (Nesco) Smart Meters
Author: Md Minhazul Haque
Author-email: mdminhazulhaque@gmail.com
Classifier: Programming Language :: Python :: 3
Classifier: License :: OSI Approved :: MIT License
Classifier: Operating System :: OS Independent
Requires-Python: >=3.6
Requires-Dist: requests
Requires-Dist: click
Requires-Dist: tabulate
Dynamic: author
Dynamic: author-email
Dynamic: classifier
Dynamic: description
Dynamic: description-content-type
Dynamic: requires-dist
Dynamic: requires-python
Dynamic: summary
